{
    "Cfg": {
        "id": "model-editor",
        "Tag": "model-editor",
        "Code": "GGRDAMQPUIDNF",
        "MaxWidth": 1,
        "ConstWidth": 1,
        "AutoUpdate": 1,
        "Adding": 1,
        "Editing": 1,
        "Deleting": 1,
        "CopySelected": 0,
        "ConstHeight": 1,
        "CanCopyPaste": 1,
        "CopyPasteTree": 1,
        "CopyFocused": 30,
        "TestIds": true,
        "HideRootTree": false,
        "AcceptDef": "",
        "SuppressCfg": 1,
        "MainCol": "Name",
        "ChildParts": 0,
        "Calculated": 1,
        "MinRowHeight": 32
    },

    "Def": [
        {
            "Name": "R",
            "DefParent": "Parent",
            "CDef": "Leaf",
            "CanDrag": "0",
            "DefEmpty": "Leaf",
            "Recalc": "256",
            "Color": "255,255,255",
            "HoverRow": "",
            "HoverCell": "",
            "FocusRow": "",
            "FocusCell": "Border",
            "Calculated": "1",
            "LowAlertCanEdit": true,
            "HighAlertCanEdit": true,
            "NameClass": "",
            "CalcOrder": "*,Target,Subtotal,SubtotalClass,ModelNameHtmlPrefix,ModelNameHtmlPostfix,ModelNameClass,TickerHtmlPrefix,TickerClass,CurrencyClass,TargetClass,PortTargetClass",
            "CalcOrder1": "PortTarget,*1",
            "SubtotalFormula": "Math.round((sum('Target') - 1)*100000000)/100000000 != 0 ?  sum('Target') - 1 : 0",
            "SubtotalClassFormula": "Math.round(Value*100000000)/100000000 !== 0 ? 'under bold' : 'equal bold'",
            "PortTargetFormula": "Parent.PortTarget === 0 ? 0 : Parent.PortTarget ?  Parent.PortTarget * Target : Root.Target * Target"
        },
        {
            "Name": "Root",
            "Expanded": true,
            "ModelNameCanEdit": false,
            "FocusCell": "Border",
            "Class": "bold padded"
        },
        {
            "Name": "Parent",
            "Class": "bold",
            "FocusCell": "Border",
            "ModelNameCanEdit": false
        },
        {
            "Name": "LeafParent",
            "Class": "bold",
            "FocusCell": "Border",
            "ModelNameCanEdit": false
        },
        {
            "Name": "EmptyParent",
            "Class": "bold",
            "ModelNameCanEdit": false,
            "FocusCell": "Border",
            "SubtotalFormula": 0
        },
        {
            "Name": "Leaf",
            "Color": "255,255,255",
            "ModelNameCanEdit": false,
            "FocusCell": "Border",
            "SubtotalVisible": 0
        },
        {
            "Name": "LinkedLeaf",
            "CanDelete": false,
            "CanEdit": false,
            "ModelNameClassFormula": "\"linkedLeaf\"",
            "SecuritySymbolClassFormula": "\"linkedLeaf\"",
            "TargetClassFormula": "\"linkedLeaf\"",
            "SubtotalClassFormula": "\"linkedLeaf\"",
            "HighAlertClassFormula": "\"linkedLeaf\"",
            "LowAlertClassFormula": "\"linkedLeaf\"",
            "PortTargetClassFormula": "\"linkedLeaf\"",
            "CurrencyClassFormula": "\"linkedLeaf\"",
            "HighLimitClass": "linkedLeaf",
            "LowLimitClass": "linkedLeaf",
            "LowAlertCanEdit": false,
            "HighAlertCanEdit": false,
            "Calculated": true,
            "Expanded": false,
            "SubtotalVisible": false,
            "TargetClass": "",
            "FocusCell": "Border",
            "HighAlertFormula": "NormalizedHighTolerance ? NormalizedHighTolerance : HighAlert",
            "LowAlertFormula": "NormalizedLowTolerance ? NormalizedLowTolerance : LowAlert"
        },
        {
            "Name": "ModelAsset",
            "ModelNameCanEdit": true,
            "FocusCell": "Border",
            "SubtotalVisible": false
        },
        {
            "Name": "ModelAssetSet",
            "ModelNameCanEdit": false,
            "FocusCell": "Border",
            "SubtotalVisible": false,
            "Calculated": 1
        },
        {
            "Name": "PortfolioModelAsset",
            "ModelNameCanEdit": false,
            "TargetClass": "",
            "FocusCell": "Border",
            "SubtotalVisible": 0,
            "Calculated": 1
        },
        {
            "Name": "RemovedSecurity",
            "CanEdit": false,
            "Class": "linkedLeaf",
            "Calculated": true,
            "Expanded": false,
            "SubtotalVisible": false,
            "TargetClass": "",
            "FocusCell": "Border"
        },
        {
            "Name": "RootLink",
            "FocusRow": "Border",
            "ModelNameCanEdit": false,
            "ModelNameHtmlPrefixFormula": "'<a style=\"margin-left:10px; \"href=\"/models/' + ModelId + '?source=' + ModelSourceType + '&isOverlay=' + IsOverlay + '\">'",
            "ModelNameHtmlPostfix": "</a>",
            "ModelNameType": "Html",
            "FocusCell": "Border",
            "Expanded": false
        },
        {
            "Name": "EmptyLinkParent",
            "FocusRow": "Border",
            "ModelNameCanEdit": false,
            "ModelNameHtmlPrefixFormula": "'<a style=\"margin-left:10px; \"href=\"/models/' + ModelId + '?source=' + ModelSourceType + '&isOverlay=' + IsOverlay + '\">'",
            "ModelNameHtmlPostfix": "</a>",
            "ModelNameType": "Html",
            "SubtotalFormula": 0,
            "FocusCell": "Border",
            "Expanded": false
        },
        {
            "Name": "Link",
            "FocusCell": "Border"
        },
        { "Name": "Classification" },
        {
            "Name": "ClassificationSet",
            "ModelNameCanEdit": false
        },
        {
            "Name": "InsertedPortfolioCash",
            "ModelNameCanEdit": false
        },
        {
            "Name": "Linked",
            "ModelNameClassFormula": "linkedLeaf",
            "ModelNameHtmlPostfix": "</a>",
            "LowAlertCanEdit": false,
            "HighAlertCanEdit": false,
            "LowAlertClass": "",
            "HighAlertClass": "",
            "TargetClass": "",
            "FocusCell": "Border",
            "CanEdit": false
        }
    ],
    "Actions": {},
    "Cols": [
        {
            "Name": "Name",
            "PrintWidth": 300,
            "RelWidth": 1,
            "MinWidth": 350,
            "Type": "Text",
            "ToolTip": 0,
            "CanFilter": 2,
            "Editor": "SecurityPicker",
            "CanSelect": 2
        },
        {
            "Name": "SecuritySymbol",
            "Visible": 1,
            "Format": "",
            "EditFormat": "",
            "CanCustomize": 0,
            "CanEdit": 0,
            "CanSearch": 0,
            "CanSort": 1,
            "ShowTip": 0,
            "Validation": "",
            "Align": "Left",
            "Type": "Html",
            "ExportValue": "SecuritySymbol",
            "HtmlPrefixFormula": "SecurityId!==null?'<a href=\\\"/securities/'+SecurityId+' \\\">':'empty'",
            "HtmlPostfix": "</a>",
            "Width": 120,
            "RelWidth": 0
        },
        {
            "Name": "Currency",
            "Visible": 1,
            "Format": "",
            "EditFormat": "",
            "CanCustomize": 0,
            "CanEdit": 0,
            "CanSearch": 0,
            "CanSort": 1,
            "ShowTip": 0,
            "Validation": "",
            "Align": "Left",
            "Type": "Text",
            "Width": 50,
            "RelWidth": 0
        },
        {
            "Name": "Target",
            "Visible": 1,
            "Format": "0.000000%;(0.000000%);0.000000%;",
            "EditFormat": "0.000000%",
            "CanCustomize": 0,
            "CanEdit": 1,
            "Edit": "{OnStartEdit: function() { this.Tag.autocomplete='off';}}",
            "CanSearch": 0,
            "CanSort": 1,
            "ShowTip": 0,
            "Validation": "",
            "Align": "Right",
            "RoundingDigits": 6,
            "Type": "Float",
            "CanEmpty": 1,
            "Width": 120,
            "RelWidth": 0
        },
        {
            "Name": "Subtotal",
            "Visible": 1,
            "Format": "0.000000%;(0.000000%);0.000000%;",
            "EditFormat": "0.00",
            "CanCustomize": 0,
            "CanEdit": 0,
            "CanSearch": 0,
            "CanSort": 1,
            "ShowTip": 0,
            "Validation": "",
            "Align": "Right",
            "RoundingDigits": 2,
            "Type": "Float",
            "CanEmpty": 1,
            "Width": 120,
            "RelWidth": 0
        },
        {
            "Name": "PortTarget",
            "Visible": 0,
            "Format": "0.00%;(0.00%);0.00%;",
            "EditFormat": "0.00",
            "CanCustomize": 0,
            "CanEdit": 0,
            "CanSearch": 0,
            "CanSort": 1,
            "ShowTip": 0,
            "Validation": "",
            "Align": "Right",
            "RoundingDigits": 2,
            "Type": "Float",
            "CanEmpty": 1,
            "Width": 120,
            "RelWidth": 0
        },
        {
            "Name": "PortfolioTarget",
            "Visible": 1,
            "Format": "0.000%;(0.000%);0.000%;",
            "EditFormat": "0.000",
            "CanCustomize": 0,
            "CanEdit": 0,
            "CanSearch": 0,
            "CanSort": 1,
            "ShowTip": 0,
            "Validation": "",
            "Align": "Right",
            "RoundingDigits": 3,
            "Type": "Float",
            "CanEmpty": 1,
            "Width": 120,
            "RelWidth": 0
        },
        {
            "Align": "Right",
            "CanCustomize": 1,
            "CanEdit": 1,
            "CanEmpty": 1,
            "CanFilter": 0,
            "CanSort": 1,
            "Edit": "{OnStartEdit: function() { this.Tag.autocomplete='off';}}",
            "EditFormat": "0.00%",
            "EmptyValue": "",
            "Format": "0.00%;,(0.00%);''",
            "Formula": "NormalizedLowTolerance",
            "Name": "LowAlert",
            "RelWidth": 0,
            "RoundingDigits": 2,
            "ShowTip": false,
            "Type": "Float",
            "Validation": "",
            "Visible": 1,
            "Width": 120
        },
        {
            "Align": "Right",
            "CanCustomize": 1,
            "CanEdit": 1,
            "CanEmpty": 1,
            "CanFilter": 0,
            "CanSort": 1,
            "Edit": "{OnStartEdit: function() { this.Tag.autocomplete='off';}}",
            "EditFormat": "0.00%",
            "EmptyValue": "",
            "Format": "0.00%;,(0.00%);''",
            "Formula": "NormalizedHighTolerance",
            "Name": "HighAlert",
            "RelWidth": 0,
            "RoundingDigits": 2,
            "ShowTip": false,
            "Type": "Float",
            "Validation": "",
            "Visible": 1,
            "Width": 120
        }
    ],
    "Header": {
        "PanelPanelSelectAllTip": 0,
        "ModelName": "Model / Security Name",
        "SecuritySymbol": "Symbol",
        "Currency": "CCY",
        "Target": "Target",
        "TargetClass": "null numeric",
        "Subtotal": "Target Error %",
        "SubtotalClass": "null numeric",
        "PortTarget": "Port. Target",
        "PortTargetClass": "null numeric",
        "PortfolioTarget": "Port. Target",
        "PortfolioTargetClass": "numeric ",
        "LowAlert": "Low Limit(-%)",
        "LowAlertClass": "null numeric",
        "HighAlert": "High Limit(+%)",
        "HighAlertClass": "null numeric",
        "LowLimit": "Low Limit",
        "LowLimitClass": "numeric ",
        "HighLimit": "High Limit",
        "HighLimitClass": "numeric ",
        "Cusip": "Cusip",
        "Ticker": "Ticker",
        "ISIN": "ISIN",
        "Sedol": "Sedol",
        "SecurityId": "SecurityId",
        "ModelType": "ModelType",
        "NormalizedLowTolerance": "NormalizedLowTolerance",
        "NormalizedHighTolerance": "NormalizedHighTolerance",
        "ClassificationId": "ClassificationId",
        "Description": "Description",
        "Rank": "Rank",
        "RankClass": "numeric ",
        "IsShort": "IsShort",
        "IsPortfolioAssignable": "IsPortfolioAssignable",
        "IsSharable": "IsSharable",
        "Parent": "Parent",
        "ModelId": "ModelId",
        "id": "id",
        "HasSubstituteDefined": "HasSubstituteDefined",
        "IsSubstitute": "IsSubstitute",
        "ModelSourceType": "ModelSourceType",
        "SourceModelId": "SourceModelId",
        "SourceModelSourceType": "SourceModelSourceType",
        "IsOverlay": "IsOverlay",
        "IsEligibleCashInstruction": "IsEligibleCashInstruction"
    },
    "Head": [
        {
            "Def": "Foot",
            "id": "Root",
            "CanDelete": 0,
            "CanEdit": 0,
            "CanAdd": 0,
            "Calculated": 1,
            "CanCopy": false,
            "CanSelect": false,
            "LowAlertCanEdit": false,
            "HighAlertCanEdit": false,
            "ModelName": "TOTAL",
            "Class": "total-row",
            "CalcOrder": "*,Target,PortTarget,PortfolioTarget,Subtotal,SubtotalClass,*1",
            "PortTargetFormula": "Target",
            "PortfolioTargetFormula": "Target",
            "TargetFormula": "sum()",
            "TargetFormat": "0.000000%",
            "TargetClass": "",
            "LowAlertClass": "",
            "HighAlertClass": "",
            "SubtotalClassFormula": "Math.round(Value*100000000)/100000000 !== 0 ? 'under' : 'equal'",
            "SubtotalFormula": "Math.round((sum('Target') - 1)*100000000)/100000000 != 0 ?  sum('Target') - 1 : 0"
        }
    ]
}
